alu.v
/*
 * Primitive alu example for Verilator example
 *
 * File name: alu.sv
 * Author: Norbertas Kremeris 2021
 *
 */


module alu #(parameter WIDTH = 32)
            (input clk,
             input rst,
             input [1:0] op_in,
             input [WIDTH-1:0] a_in,
             input [WIDTH-1:0] b_in,
             input in_valid,
             output [WIDTH-1:0] out,
             output out_valid);
    
    reg  [WIDTH-1:0]  a_in_r;
    reg  [WIDTH-1:0]  b_in_r;
    reg               in_valid_r;
    reg  [WIDTH-1:0]  result;
    reg  [1:0] op_in_r;
    reg   done;
    
    localparam  add = 1;
    localparam  sub = 2;
    localparam  nop = 0;
    
    // Register all inputs
    always @ (posedge clk, posedge rst)
    begin
        if (rst == 1)
        begin
            op_in_r    <= '0;
            a_in_r     <= '0;
            b_in_r     <= '0;
            in_valid_r <= '0;
        end
        else
        begin
            op_in_r    <= op_in;
            a_in_r     <= a_in;
            b_in_r     <= b_in;
            in_valid_r <= in_valid;
            done       <= 0;
            
            if (in_valid_r == 1)
            begin
                case (op_in_r)
                    add: result     <= a_in_r + b_in_r;
                    sub: result     <= a_in_r + (~b_in_r+1'b1);
                    default: result <= '0;
                endcase
                done <= 1;
            end
            else
            begin
                result <= '0;
            end
            
        end
    end
    
    assign out       = result;
    assign out_valid = done;
    
    endmodule;

waveform.vcd
$version Generated by VerilatedVcd $end
$date Wed Mar  9 21:47:56 2022
 $end
$timescale   1ns $end

 $scope module TOP $end
  $var wire 32 k a_in [31:0] $end
  $var wire 32 s b_in [31:0] $end
  $var wire  1 S clk $end
  $var wire  1 { in_valid $end
  $var wire  2 c op_in [1:0] $end
  $var wire 32 %! out [31:0] $end
  $var wire  1 -! out_valid $end
  $var wire  1 [ rst $end
  $scope module alu $end
   $var wire 32 5! WIDTH [31:0] $end
   $var wire 32 k a_in [31:0] $end
   $var wire 32 # a_in_r [31:0] $end
   $var wire 32 =! add [31:0] $end
   $var wire 32 s b_in [31:0] $end
   $var wire 32 + b_in_r [31:0] $end
   $var wire  1 S clk $end
   $var wire  1 K done $end
   $var wire  1 { in_valid $end
   $var wire  1 3 in_valid_r $end
   $var wire 32 M! nop [31:0] $end
   $var wire  2 c op_in [1:0] $end
   $var wire  2 C op_in_r [1:0] $end
   $var wire 32 %! out [31:0] $end
   $var wire  1 -! out_valid $end
   $var wire 32 ; result [31:0] $end
   $var wire  1 [ rst $end
   $var wire 32 E! sub [31:0] $end
  $upscope $end
 $upscope $end
$enddefinitions $end


#0
b10000000100110101000010000011001 #
b11010110100011100000010010111000 +
13
b00110101011110011110001111000110 ;
b01 C
1K
0S
0[
b10 c
b01100000001001010100011010010001 k
b10001001010010000100110010001011 s
0{
b00110101011110011110001111000110 %!
1-!
b00000000000000000000000000100000 5!
b00000000000000000000000000000001 =!
b00000000000000000000000000000010 E!
b00000000000000000000000000000000 M!
#1
b01100000001001010100011010010001 #
b10001001010010000100110010001011 +
03
b01010111001010001000100011010001 ;
b10 C
1S
b01010111001010001000100011010001 %!
#2
0S
#3
b00000000000000000000000000000000 #
b00000000000000000000000000000000 +
b00 C
1S
1[
b00 c
b00000000000000000000000000000000 k
b00000000000000000000000000000000 s
#4
0S
#5
1S
#6
0S
0[
#7
b00000000000000000000000000000000 ;
0K
1S
b00000000000000000000000000000000 %!
0-!
#8
0S
#9
1S
#10
0S
#11
1S
#12
0S
#13
1S
#14
0S
#15
1S
#16
0S
#17
1S
#18
0S
#19
1S
#20
0S
#21
1S
b10 c
b00000000000000000000000000001100 k
b00000000000000000000000000000100 s
1{
#22
0S
#23
b00000000000000000000000000001100 #
b00000000000000000000000000000100 +
13
b10 C
1S
0{
#24
0S
#25
03
b00000000000000000000000000001000 ;
1K
1S
b00000000000000000000000000001010 k
b00000000000000000000000000000001 s
1{
b00000000000000000000000000001000 %!
1-!
#26
0S
#27
b00000000000000000000000000001010 #
b00000000000000000000000000000001 +
13
b00000000000000000000000000000000 ;
0K
1S
0{
b00000000000000000000000000000000 %!
0-!
#28
0S
#29
03
b00000000000000000000000000001001 ;
1K
1S
b00000000000000000000000000001001 %!
1-!
#30
0S
#31
b00000000000000000000000000000000 ;
0K
1S
b00000000000000000000000000000000 %!
0-!
#32
0S
#33
1S
b01 c
b00000000000000000000000000010010 k
b00000000000000000000000000000000 s
1{
#34
0S
#35
b00000000000000000000000000010010 #
b00000000000000000000000000000000 +
13
b01 C
1S
0{
#36
0S
#37
03
b00000000000000000000000000010010 ;
1K
1S
b10 c
b00000000000000000000000000001101 k
b00000000000000000000000000000011 s
1{
b00000000000000000000000000010010 %!
1-!
#38
0S
#39
b00000000000000000000000000001101 #
b00000000000000000000000000000011 +
13
b00000000000000000000000000000000 ;
b10 C
0K
1S
0{
b00000000000000000000000000000000 %!
0-!
#40
0S
#41
03
b00000000000000000000000000001010 ;
1K
1S
b00000000000000000000000000001010 %!
1-!
#42
0S
#43
b00000000000000000000000000000000 ;
0K
1S
b00000000000000000000000000000000 %!
0-!
#44
0S
#45
1S
#46
0S
#47
1S
b00000000000000000000000000010001 k
b00000000000000000000000000000101 s
1{
#48
0S
#49
b00000000000000000000000000010001 #
b00000000000000000000000000000101 +
13
1S
b00000000000000000000000000001110 k
b00000000000000000000000000000100 s
#50
0S
#51
b00000000000000000000000000001110 #
b00000000000000000000000000000100 +
b00000000000000000000000000001100 ;
1K
1S
b01 c
b00000000000000000000000000001011 k
b00000000000000000000000000000011 s
b00000000000000000000000000001100 %!
1-!
#52
0S
#53
b00000000000000000000000000001011 #
b00000000000000000000000000000011 +
b00000000000000000000000000001010 ;
b01 C
1S
0{
b00000000000000000000000000001010 %!
#54
0S
#55
03
b00000000000000000000000000001110 ;
1S
b10 c
b00000000000000000000000000010001 k
b00000000000000000000000000000010 s
1{
b00000000000000000000000000001110 %!
#56
0S
#57
b00000000000000000000000000010001 #
b00000000000000000000000000000010 +
13
b00000000000000000000000000000000 ;
b10 C
0K
1S
0{
b00000000000000000000000000000000 %!
0-!
#58
0S
#59
03
b00000000000000000000000000001111 ;
1K
1S
b00000000000000000000000000001111 %!
1-!
#60
0S
#61
b00000000000000000000000000000000 ;
0K
1S
b00000000000000000000000000000000 %!
0-!
#62
0S
#63
1S
#64
0S
#65
1S
b01 c
b00000000000000000000000000001011 k
b00000000000000000000000000000100 s
1{
#66
0S
#67
b00000000000000000000000000001011 #
b00000000000000000000000000000100 +
13
b01 C
1S
0{
#68
0S
#69
03
b00000000000000000000000000001111 ;
1K
1S
b00000000000000000000000000001111 %!
1-!
#70
0S
#71
b00000000000000000000000000000000 ;
0K
1S
b10 c
b00000000000000000000000000010100 k
b00000000000000000000000000000010 s
1{
b00000000000000000000000000000000 %!
0-!
#72
0S
#73
b00000000000000000000000000010100 #
b00000000000000000000000000000010 +
13
b10 C
1S
0{
#74
0S
#75
03
b00000000000000000000000000010010 ;
1K
1S
b00000000000000000000000000010010 %!
1-!
#76
0S
#77
b00000000000000000000000000000000 ;
0K
1S
b00000000000000000000000000001101 k
b00000000000000000000000000000100 s
1{
b00000000000000000000000000000000 %!
0-!
#78
0S
#79
b00000000000000000000000000001101 #
b00000000000000000000000000000100 +
13
1S
0{
#80
0S
#81
03
b00000000000000000000000000001001 ;
1K
1S
b00000000000000000000000000010001 k
b00000000000000000000000000000101 s
1{
b00000000000000000000000000001001 %!
1-!
#82
0S
#83
b00000000000000000000000000010001 #
b00000000000000000000000000000101 +
13
b00000000000000000000000000000000 ;
0K
1S
0{
b00000000000000000000000000000000 %!
0-!
#84
0S
#85
03
b00000000000000000000000000001100 ;
1K
1S
b01 c
b00000000000000000000000000000000 s
1{
b00000000000000000000000000001100 %!
1-!
#86
0S
#87
b00000000000000000000000000000000 +
13
b00000000000000000000000000000000 ;
b01 C
0K
1S
0{
b00000000000000000000000000000000 %!
0-!
#88
0S
#89
03
b00000000000000000000000000010001 ;
1K
1S
b00000000000000000000000000010001 %!
1-!
#90
0S
#91
b00000000000000000000000000000000 ;
0K
1S
b00000000000000000000000000001101 k
1{
b00000000000000000000000000000000 %!
0-!
#92
0S
#93
b00000000000000000000000000001101 #
13
1S
0{
#94
0S
#95
03
b00000000000000000000000000001101 ;
1K
1S
b00000000000000000000000000001101 %!
1-!
#96
0S
#97
b00000000000000000000000000000000 ;
0K
1S
b00000000000000000000000000000000 %!
0-!
#98
0S
#99
1S
#100
0S
#101
1S
#102
0S
#103
1S
#104
0S
#105
1S
#106
0S
#107
1S
#108
0S
#109
1S
#110
0S
#111
1S
#112
0S
#113
1S
#114
0S
#115
1S
#116
0S
#117
1S
b10 c
b00000000000000000000000000000001 s
1{
#118
0S
#119
b00000000000000000000000000000001 +
13
b10 C
1S
0{
#120
0S
#121
03
b00000000000000000000000000001100 ;
1K
1S
b00000000000000000000000000001100 %!
1-!
#122
0S
#123
b00000000000000000000000000000000 ;
0K
1S
b00000000000000000000000000000000 %!
0-!
#124
0S
#125
1S
#126
0S
#127
1S
#128
0S
#129
1S
#130
0S
#131
1S
#132
0S
#133
1S
#134
0S
#135
1S
#136
0S
#137
1S
#138
0S
#139
1S
#140
0S
#141
1S
#142
0S
#143
1S
#144
0S
#145
1S
#146
0S
#147
1S
#148
0S
#149
1S
#150
0S
#151
1S
#152
0S
#153
1S
#154
0S
#155
1S
#156
0S
#157
1S
#158
0S
#159
1S
#160
0S
#161
1S
#162
0S
#163
1S
b01 c
b00000000000000000000000000010011 k
b00000000000000000000000000000101 s
1{
#164
0S
#165
b00000000000000000000000000010011 #
b00000000000000000000000000000101 +
13
b01 C
1S
b00000000000000000000000000001101 k
#166
0S
#167
b00000000000000000000000000001101 #
b00000000000000000000000000011000 ;
1K
1S
0{
b00000000000000000000000000011000 %!
1-!
#168
0S
#169
03
b00000000000000000000000000010010 ;
1S
b00000000000000000000000000010010 %!
#170
0S
#171
b00000000000000000000000000000000 ;
0K
1S
b00000000000000000000000000000000 %!
0-!
